asyncorm/__init__.py
asyncorm/exceptions.py
asyncorm/test_case.py
asyncorm/application/__init__.py
asyncorm/application/configure.py
asyncorm/application/commands/__init__.py
asyncorm/application/commands/migrator.py
asyncorm/application/commands/orm_setup.py
asyncorm/apps/__init__.py
asyncorm/apps/app.py
asyncorm/apps/app_config.py
asyncorm/apps/app_migration.py
asyncorm/database/__init__.py
asyncorm/database/cursor.py
asyncorm/database/query_stack.py
asyncorm/database/backends/__init__.py
asyncorm/database/backends/postgres_backend.py
asyncorm/database/backends/sql_base_backend.py
asyncorm/log/__init__.py
asyncorm/manager/__init__.py
asyncorm/manager/constants.py
asyncorm/manager/model_manager.py
asyncorm/manager/queryset.py
asyncorm/migrations/__init__.py
asyncorm/migrations/app.py
asyncorm/migrations/models.py
asyncorm/migrations/migrations/0001__initial_9067a6f99031.py
asyncorm/models/__init__.py
asyncorm/models/field.py
asyncorm/models/fields.py
asyncorm/models/models.py
asyncorm/orm_migrations/__init__.py
asyncorm/orm_migrations/app_migrator.py
asyncorm/orm_migrations/migration_actions.py
asyncorm/orm_migrations/migration_constructor.py
asyncorm/serializers/__init__.py
asyncorm/serializers/serializer.py
asyncorm-0.5.3.dist-info/LICENSE
asyncorm-0.5.3.dist-info/METADATA
asyncorm-0.5.3.dist-info/WHEEL
asyncorm-0.5.3.dist-info/entry_points.txt
asyncorm-0.5.3.dist-info/top_level.txt
asyncorm-0.5.3.dist-info/RECORD
