Metadata-Version: 2.1
Name: asyncorm
Version: 0.5.3
Summary: A fully asynchronous python ORM
Home-page: https://github.com/monobot/asyncorm
Author: Héctor Alvarez (monobot)
Author-email: monobot.soft@gmail.com
License: Apache Software License 2.0
Keywords: asyncorm
Platform: UNKNOWN
Classifier: Development Status :: 3 - Alpha
Classifier: Framework :: AsyncIO
Classifier: Intended Audience :: Developers
Classifier: License :: OSI Approved :: Apache Software License
Classifier: Natural Language :: English
Classifier: Programming Language :: Python :: 3.5
Classifier: Programming Language :: Python :: 3.6
Classifier: Programming Language :: Python :: 3.7
Classifier: Programming Language :: Python :: 3.8
Classifier: Topic :: Database
Requires-Dist: asyncpg (>=0.18.3)
Requires-Dist: netaddr (>=0.7.19)
